velorail/__init__.py
velorail/explore.py
velorail/explore_view.py
velorail/gpxviewer.py
velorail/kgwalker.py
velorail/locfind.py
velorail/npq.py
velorail/osm2wiki.py
velorail/querygen.py
velorail/sso_users_solution.py
velorail/tour.py
velorail/velorail_cmd.py
velorail/version.py
velorail/wditem_search.py
velorail/webserver.py
velorail/wkt.py
velorail/resources/endpoints.yaml
velorail/resources/queries/locations.yaml
velorail/resources/queries/osmplanet.yaml
velorail/resources/queries/osmplanet_explore.yaml
velorail/resources/queries/sparql-explore.yaml
velorail-0.1.0.dist-info/METADATA
velorail-0.1.0.dist-info/WHEEL
velorail-0.1.0.dist-info/entry_points.txt
velorail-0.1.0.dist-info/licenses/LICENSE
velorail-0.1.0.dist-info/RECORD
